nonion/__init__.py
nonion/nonion.py
nonion/tools/__init__.py
nonion/tools/tools.py
nonion-0.4.4.dist-info/LICENSE.md
nonion-0.4.4.dist-info/METADATA
nonion-0.4.4.dist-info/WHEEL
nonion-0.4.4.dist-info/top_level.txt
nonion-0.4.4.dist-info/RECORD
