Metadata-Version: 2.1
Name: nonion
Version: 0.4.4
Summary: Python Functional Programming for Humans.
Home-page: https://bitbucket.org/shkroba/nonion
Author: Illia Shkroba
Author-email: is@pjwstk.edu.pl
Classifier: Intended Audience :: Developers
Classifier: License :: OSI Approved :: GNU Lesser General Public License v3 (LGPLv3)
Classifier: Operating System :: OS Independent
Classifier: Programming Language :: Python :: 3.6
Classifier: Topic :: Software Development :: Libraries :: Application Frameworks
Classifier: Typing :: Typed
Requires-Python: >=3.6
License-File: LICENSE.md
